amap_poi/__init__.py
amap_poi-0.0.2.data/scripts/amap-poi
amap_poi-0.0.2.dist-info/LICENSE
amap_poi-0.0.2.dist-info/METADATA
amap_poi-0.0.2.dist-info/WHEEL
amap_poi-0.0.2.dist-info/top_level.txt
amap_poi-0.0.2.dist-info/RECORD
